rrytapi/.DS_Store
rrytapi/__init__.py
rrytapi/htmlsoup.py
rrytapi/player.py
rrytapi/playlist.py
rrytapi/searcher.py
rrytapi/utils.py
rrytapi/video.py
rrytapi/videoformats.py
rrytapi-2.1.0.dist-info/METADATA
rrytapi-2.1.0.dist-info/WHEEL
rrytapi-2.1.0.dist-info/RECORD
