Metadata-Version: 2.1
Name: rrytapi
Version: 2.1.0
Summary: 
License: MIT
Author: RadoTheProgrammer
Author-email: rado@arazakar.com
Requires-Python: >=3.11,<4.0
Classifier: License :: OSI Approved :: MIT License
Classifier: Programming Language :: Python :: 3
Classifier: Programming Language :: Python :: 3.11
Classifier: Programming Language :: Python :: 3.12
Requires-Dist: bs4 (>=0.0.2,<0.0.3)
Requires-Dist: clean-text (>=0.6.0,<0.7.0)
Requires-Dist: js2py (>=0.74,<0.75)
Requires-Dist: mini-lambda (>=2.2.3,<3.0.0)
Requires-Dist: pydub (>=0.25.1)
Requires-Dist: requests (>=2.31.0,<3.0.0)
Requires-Dist: rrprettier (>=1.0.0,<2.0.0)
Requires-Dist: unidecode (>=1.3.8,<2.0.0)
